bapp_framework_sdk/__init__.py
bapp_framework_sdk/client.py
bapp_framework_sdk-2.0.13001.dist-info/METADATA
bapp_framework_sdk-2.0.13001.dist-info/WHEEL
bapp_framework_sdk-2.0.13001.dist-info/RECORD
