Metadata-Version: 2.4
Name: bapp-framework-sdk
Version: 2.0.13001
Summary: The APi client to be used for the BApp Framework
License: MIT
Author: Cristi Boboc
Author-email: cristi@cbsoft.ro
Requires-Python: >=3.8
Classifier: License :: OSI Approved :: MIT License
Classifier: Programming Language :: Python :: 3
Classifier: Programming Language :: Python :: 3.8
Classifier: Programming Language :: Python :: 3.9
Classifier: Programming Language :: Python :: 3.10
Classifier: Programming Language :: Python :: 3.11
Classifier: Programming Language :: Python :: 3.12
Classifier: Programming Language :: Python :: 3.13
Classifier: Programming Language :: Python :: 3.14
Requires-Dist: requests (>=2.32.3,<3.0.0)
